{
  "1": [
    {
      "word": "πᾶς",
      "lemma": "πᾶς",
      "strongs": "G39560",
      "morph": "Gr,RI,,,,NMS,"
    },
    {
      "word": "ὁ",
      "lemma": "ὁ",
      "strongs": "G35880",
      "morph": "Gr,RD,,,,NMS,"
    },
    {
      "word": "πιστεύων",
      "lemma": "πιστεύω",
      "strongs": "G41000",
      "morph": "Gr,V,PPA,NMS,"
    },
    {
      "word": "ὅτι",
      "lemma": "ὅτι",
      "strongs": "G37540",
      "morph": "Gr,CS,,,,,,,,"
    },
    {
      "word": "Ἰησοῦς",
      "lemma": "Ἰησοῦς",
      "strongs": "G24240",
      "morph": "Gr,N,,,,,NMS,"
    },
    {
      "word": "ἐστιν",
      "lemma": "εἰμί",
      "strongs": "G15100",
      "morph": "Gr,V,IPA3,,S,"
    },
    {
      "word": "ὁ",
      "lemma": "ὁ",
      "strongs": "G35880",
      "morph": "Gr,EA,,,,NMS,"
    },
    {
      "word": "Χριστὸς",
      "lemma": "χριστός",
      "strongs": "G55470",
      "morph": "Gr,N,,,,,NMS,"
    },
    {
      "word": "ἐκ",
      "lemma": "ἐκ",
      "strongs": "G15370",
      "morph": "Gr,P,,,,,G,,,"
    },
    {
      "word": "τοῦ",
      "lemma": "ὁ",
      "strongs": "G35880",
      "morph": "Gr,EA,,,,GMS,"
    },
    {
      "word": "Θεοῦ",
      "lemma": "θεός",
      "strongs": "G23160",
      "morph": "Gr,N,,,,,GMS,"
    },
    {
      "word": "γεγέννηται",
      "lemma": "γεννάω",
      "strongs": "G10800",
      "morph": "Gr,V,IEP3,,S,"
    },
    {
      "word": "καὶ",
      "lemma": "καί",
      "strongs": "G25320",
      "morph": "Gr,CC,,,,,,,,"
    },
    {
      "word": "πᾶς",
      "lemma": "πᾶς",
      "strongs": "G39560",
      "morph": "Gr,RI,,,,NMS,"
    },
    {
      "word": "ὁ",
      "lemma": "ὁ",
      "strongs": "G35880",
      "morph": "Gr,RD,,,,NMS,"
    },
    {
      "word": "ἀγαπῶν",
      "lemma": "ἀγαπάω",
      "strongs": "G00250",
      "morph": "Gr,V,PPA,NMS,"
    },
    {
      "word": "τὸν",
      "lemma": "ὁ",
      "strongs": "G35880",
      "morph": "Gr,RD,,,,AMS,"
    },
    {
      "word": "γεννήσαντα",
      "lemma": "γεννάω",
      "strongs": "G10800",
      "morph": "Gr,V,PAA,AMS,"
    },
    {
      "word": "ἀγαπᾷ",
      "lemma": "ἀγαπάω",
      "strongs": "G00250",
      "morph": "Gr,V,IPA3,,S,"
    },
    {
      "word": "καὶ",
      "lemma": "καί",
      "strongs": "G25320",
      "morph": "Gr,D,,,,,,,,,"
    },
    {
      "word": "τὸν",
      "lemma": "ὁ",
      "strongs": "G35880",
      "morph": "Gr,RD,,,,AMS,"
    },
    {
      "word": "γεγεννημένον",
      "lemma": "γεννάω",
      "strongs": "G10800",
      "morph": "Gr,V,PEP,AMS,"
    },
    {
      "word": "ἐξ",
      "lemma": "ἐκ",
      "strongs": "G15370",
      "morph": "Gr,P,,,,,G,,,"
    },
    {
      "word": "αὐτοῦ",
      "lemma": "αὐτός",
      "strongs": "G08460",
      "morph": "Gr,RP,,,3GMS,"
    }
  ],
  "2": [
    {
      "word": "ἐν",
      "lemma": "ἐν",
      "strongs": "G17220",
      "morph": "Gr,P,,,,,D,,,"
    },
    {
      "word": "τούτῳ",
      "lemma": "οὗτος",
      "strongs": "G37780",
      "morph": "Gr,RD,,,,DNS,"
    },
    {
      "word": "γινώσκομεν",
      "lemma": "γινώσκω",
      "strongs": "G10970",
      "morph": "Gr,V,IPA1,,P,"
    },
    {
      "word": "ὅτι",
      "lemma": "ὅτι",
      "strongs": "G37540",
      "morph": "Gr,CS,,,,,,,,"
    },
    {
      "word": "ἀγαπῶμεν",
      "lemma": "ἀγαπάω",
      "strongs": "G00250",
      "morph": "Gr,V,IPA1,,P,"
    },
    {
      "word": "τὰ",
      "lemma": "ὁ",
      "strongs": "G35880",
      "morph": "Gr,EA,,,,ANP,"
    },
    {
      "word": "τέκνα",
      "lemma": "τέκνον",
      "strongs": "G50430",
      "morph": "Gr,N,,,,,ANP,"
    },
    {
      "word": "τοῦ",
      "lemma": "ὁ",
      "strongs": "G35880",
      "morph": "Gr,EA,,,,GMS,"
    },
    {
      "word": "Θεοῦ",
      "lemma": "θεός",
      "strongs": "G23160",
      "morph": "Gr,N,,,,,GMS,"
    },
    {
      "word": "ὅταν",
      "lemma": "ὅταν",
      "strongs": "G37520",
      "morph": "Gr,CS,,,,,,,,"
    },
    {
      "word": "τὸν",
      "lemma": "ὁ",
      "strongs": "G35880",
      "morph": "Gr,EA,,,,AMS,"
    },
    {
      "word": "Θεὸν",
      "lemma": "θεός",
      "strongs": "G23160",
      "morph": "Gr,N,,,,,AMS,"
    },
    {
      "word": "ἀγαπῶμεν",
      "lemma": "ἀγαπάω",
      "strongs": "G00250",
      "morph": "Gr,V,IPA1,,P,"
    },
    {
      "word": "καὶ",
      "lemma": "καί",
      "strongs": "G25320",
      "morph": "Gr,CC,,,,,,,,"
    },
    {
      "word": "τὰς",
      "lemma": "ὁ",
      "strongs": "G35880",
      "morph": "Gr,EA,,,,AFP,"
    },
    {
      "word": "ἐντολὰς",
      "lemma": "ἐντολή",
      "strongs": "G17850",
      "morph": "Gr,N,,,,,AFP,"
    },
    {
      "word": "αὐτοῦ",
      "lemma": "αὐτός",
      "strongs": "G08460",
      "morph": "Gr,RP,,,3GMS,"
    },
    {
      "word": "τηρῶμεν",
      "lemma": "τηρέω",
      "strongs": "G50830",
      "morph": "Gr,V,SPA1,,P,"
    }
  ],
  "3": [
    {
      "word": "αὕτη",
      "lemma": "οὗτος",
      "strongs": "G37780",
      "morph": "Gr,RD,,,,NFS,"
    },
    {
      "word": "γάρ",
      "lemma": "γάρ",
      "strongs": "G10630",
      "morph": "Gr,CC,,,,,,,,"
    },
    {
      "word": "ἐστιν",
      "lemma": "εἰμί",
      "strongs": "G15100",
      "morph": "Gr,V,IPA3,,S,"
    },
    {
      "word": "ἡ",
      "lemma": "ὁ",
      "strongs": "G35880",
      "morph": "Gr,EA,,,,NFS,"
    },
    {
      "word": "ἀγάπη",
      "lemma": "ἀγάπη",
      "strongs": "G00260",
      "morph": "Gr,N,,,,,NFS,"
    },
    {
      "word": "τοῦ",
      "lemma": "ὁ",
      "strongs": "G35880",
      "morph": "Gr,EA,,,,GMS,"
    },
    {
      "word": "Θεοῦ",
      "lemma": "θεός",
      "strongs": "G23160",
      "morph": "Gr,N,,,,,GMS,"
    },
    {
      "word": "ἵνα",
      "lemma": "ἵνα",
      "strongs": "G24430",
      "morph": "Gr,D,,,,,,,,,"
    },
    {
      "word": "τὰς",
      "lemma": "ὁ",
      "strongs": "G35880",
      "morph": "Gr,EA,,,,AFP,"
    },
    {
      "word": "ἐντολὰς",
      "lemma": "ἐντολή",
      "strongs": "G17850",
      "morph": "Gr,N,,,,,AFP,"
    },
    {
      "word": "αὐτοῦ",
      "lemma": "αὐτός",
      "strongs": "G08460",
      "morph": "Gr,RP,,,3GMS,"
    },
    {
      "word": "τηρῶμεν",
      "lemma": "τηρέω",
      "strongs": "G50830",
      "morph": "Gr,V,SPA1,,P,"
    },
    {
      "word": "καὶ",
      "lemma": "καί",
      "strongs": "G25320",
      "morph": "Gr,CC,,,,,,,,"
    },
    {
      "word": "αἱ",
      "lemma": "ὁ",
      "strongs": "G35880",
      "morph": "Gr,EA,,,,NFP,"
    },
    {
      "word": "ἐντολαὶ",
      "lemma": "ἐντολή",
      "strongs": "G17850",
      "morph": "Gr,N,,,,,NFP,"
    },
    {
      "word": "αὐτοῦ",
      "lemma": "αὐτός",
      "strongs": "G08460",
      "morph": "Gr,RP,,,3GMS,"
    },
    {
      "word": "βαρεῖαι",
      "lemma": "βαρύς",
      "strongs": "G09260",
      "morph": "Gr,NP,,,,NFP,"
    },
    {
      "word": "οὐκ",
      "lemma": "οὐ",
      "strongs": "G37560",
      "morph": "Gr,D,,,,,,,,,"
    },
    {
      "word": "εἰσίν",
      "lemma": "εἰμί",
      "strongs": "G15100",
      "morph": "Gr,V,IPA3,,P,"
    }
  ],
  "4": [
    {
      "word": "ὅτι",
      "lemma": "ὅτι",
      "strongs": "G37540",
      "morph": "Gr,CS,,,,,,,,"
    },
    {
      "word": "πᾶν",
      "lemma": "πᾶς",
      "strongs": "G39560",
      "morph": "Gr,RI,,,,NNS,"
    },
    {
      "word": "τὸ",
      "lemma": "ὁ",
      "strongs": "G35880",
      "morph": "Gr,RD,,,,NNS,"
    },
    {
      "word": "γεγεννημένον",
      "lemma": "γεννάω",
      "strongs": "G10800",
      "morph": "Gr,V,PEP,NNS,"
    },
    {
      "word": "ἐκ",
      "lemma": "ἐκ",
      "strongs": "G15370",
      "morph": "Gr,P,,,,,G,,,"
    },
    {
      "word": "τοῦ",
      "lemma": "ὁ",
      "strongs": "G35880",
      "morph": "Gr,EA,,,,GMS,"
    },
    {
      "word": "Θεοῦ",
      "lemma": "θεός",
      "strongs": "G23160",
      "morph": "Gr,N,,,,,GMS,"
    },
    {
      "word": "νικᾷ",
      "lemma": "νικάω",
      "strongs": "G35280",
      "morph": "Gr,V,IPA3,,S,"
    },
    {
      "word": "τὸν",
      "lemma": "ὁ",
      "strongs": "G35880",
      "morph": "Gr,EA,,,,AMS,"
    },
    {
      "word": "κόσμον",
      "lemma": "κόσμος",
      "strongs": "G28890",
      "morph": "Gr,N,,,,,AMS,"
    },
    {
      "word": "καὶ",
      "lemma": "καί",
      "strongs": "G25320",
      "morph": "Gr,CC,,,,,,,,"
    },
    {
      "word": "αὕτη",
      "lemma": "οὗτος",
      "strongs": "G37780",
      "morph": "Gr,RD,,,,NFS,"
    },
    {
      "word": "ἐστὶν",
      "lemma": "εἰμί",
      "strongs": "G15100",
      "morph": "Gr,V,IPA3,,S,"
    },
    {
      "word": "ἡ",
      "lemma": "ὁ",
      "strongs": "G35880",
      "morph": "Gr,EA,,,,NFS,"
    },
    {
      "word": "νίκη",
      "lemma": "νίκη",
      "strongs": "G35290",
      "morph": "Gr,N,,,,,NFS,"
    },
    {
      "word": "ἡ",
      "lemma": "ὁ",
      "strongs": "G35880",
      "morph": "Gr,RD,,,,NFS,"
    },
    {
      "word": "νικήσασα",
      "lemma": "νικάω",
      "strongs": "G35280",
      "morph": "Gr,V,PAA,NFS,"
    },
    {
      "word": "τὸν",
      "lemma": "ὁ",
      "strongs": "G35880",
      "morph": "Gr,EA,,,,AMS,"
    },
    {
      "word": "κόσμον",
      "lemma": "κόσμος",
      "strongs": "G28890",
      "morph": "Gr,N,,,,,AMS,"
    },
    {
      "word": "ἡ",
      "lemma": "ὁ",
      "strongs": "G35880",
      "morph": "Gr,EA,,,,NFS,"
    },
    {
      "word": "πίστις",
      "lemma": "πίστις",
      "strongs": "G41020",
      "morph": "Gr,N,,,,,NFS,"
    },
    {
      "word": "ἡμῶν",
      "lemma": "ἐγώ",
      "strongs": "G14730",
      "morph": "Gr,RP,,,1G,P,"
    }
  ],
  "5": [
    {
      "word": "τίς",
      "lemma": "τίς",
      "strongs": "G51010",
      "morph": "Gr,RT,,,,NMS,"
    },
    {
      "word": "ἐστιν",
      "lemma": "εἰμί",
      "strongs": "G15100",
      "morph": "Gr,V,IPA3,,S,"
    },
    {
      "word": "δέ",
      "lemma": "δέ",
      "strongs": "G11610",
      "morph": "Gr,CC,,,,,,,,"
    },
    {
      "word": "ὁ",
      "lemma": "ὁ",
      "strongs": "G35880",
      "morph": "Gr,RD,,,,NMS,"
    },
    {
      "word": "νικῶν",
      "lemma": "νικάω",
      "strongs": "G35280",
      "morph": "Gr,V,PPA,NMS,"
    },
    {
      "word": "τὸν",
      "lemma": "ὁ",
      "strongs": "G35880",
      "morph": "Gr,EA,,,,AMS,"
    },
    {
      "word": "κόσμον",
      "lemma": "κόσμος",
      "strongs": "G28890",
      "morph": "Gr,N,,,,,AMS,"
    },
    {
      "word": "εἰ",
      "lemma": "εἰ",
      "strongs": "G14870",
      "morph": "Gr,PI,,,,,,,,"
    },
    {
      "word": "μὴ",
      "lemma": "μή",
      "strongs": "G33610",
      "morph": "Gr,D,,,,,,,,,"
    },
    {
      "word": "ὁ",
      "lemma": "ὁ",
      "strongs": "G35880",
      "morph": "Gr,RD,,,,NMS,"
    },
    {
      "word": "πιστεύων",
      "lemma": "πιστεύω",
      "strongs": "G41000",
      "morph": "Gr,V,PPA,NMS,"
    },
    {
      "word": "ὅτι",
      "lemma": "ὅτι",
      "strongs": "G37540",
      "morph": "Gr,CS,,,,,,,,"
    },
    {
      "word": "Ἰησοῦς",
      "lemma": "Ἰησοῦς",
      "strongs": "G24240",
      "morph": "Gr,N,,,,,NMS,"
    },
    {
      "word": "ἐστιν",
      "lemma": "εἰμί",
      "strongs": "G15100",
      "morph": "Gr,V,IPA3,,S,"
    },
    {
      "word": "ὁ",
      "lemma": "ὁ",
      "strongs": "G35880",
      "morph": "Gr,EA,,,,NMS,"
    },
    {
      "word": "Υἱὸς",
      "lemma": "υἱός",
      "strongs": "G52070",
      "morph": "Gr,N,,,,,NMS,"
    },
    {
      "word": "τοῦ",
      "lemma": "ὁ",
      "strongs": "G35880",
      "morph": "Gr,EA,,,,GMS,"
    },
    {
      "word": "Θεοῦ",
      "lemma": "θεός",
      "strongs": "G23160",
      "morph": "Gr,N,,,,,GMS,"
    }
  ],
  "6": [
    {
      "word": "οὗτός",
      "lemma": "οὗτος",
      "strongs": "G37780",
      "morph": "Gr,RD,,,,NMS,"
    },
    {
      "word": "ἐστιν",
      "lemma": "εἰμί",
      "strongs": "G15100",
      "morph": "Gr,V,IPA3,,S,"
    },
    {
      "word": "ὁ",
      "lemma": "ὁ",
      "strongs": "G35880",
      "morph": "Gr,RD,,,,NMS,"
    },
    {
      "word": "ἐλθὼν",
      "lemma": "ἔρχομαι",
      "strongs": "G20640",
      "morph": "Gr,V,PAA,NMS,"
    },
    {
      "word": "δι’",
      "lemma": "διά",
      "strongs": "G12230",
      "morph": "Gr,P,,,,,G,,,"
    },
    {
      "word": "ὕδατος",
      "lemma": "ὕδωρ",
      "strongs": "G52040",
      "morph": "Gr,N,,,,,GNS,"
    },
    {
      "word": "καὶ",
      "lemma": "καί",
      "strongs": "G25320",
      "morph": "Gr,CC,,,,,,,,"
    },
    {
      "word": "αἵματος",
      "lemma": "αἷμα",
      "strongs": "G01290",
      "morph": "Gr,N,,,,,GNS,"
    },
    {
      "word": "Ἰησοῦς",
      "lemma": "Ἰησοῦς",
      "strongs": "G24240",
      "morph": "Gr,N,,,,,NMS,"
    },
    {
      "word": "Χριστός",
      "lemma": "χριστός",
      "strongs": "G55470",
      "morph": "Gr,N,,,,,NMS,"
    },
    {
      "word": "οὐκ",
      "lemma": "οὐ",
      "strongs": "G37560",
      "morph": "Gr,DO,,,,,,,,"
    },
    {
      "word": "ἐν",
      "lemma": "ἐν",
      "strongs": "G17220",
      "morph": "Gr,P,,,,,D,,,"
    },
    {
      "word": "τῷ",
      "lemma": "ὁ",
      "strongs": "G35880",
      "morph": "Gr,EA,,,,DNS,"
    },
    {
      "word": "ὕδατι",
      "lemma": "ὕδωρ",
      "strongs": "G52040",
      "morph": "Gr,N,,,,,DNS,"
    },
    {
      "word": "μόνον",
      "lemma": "μόνον",
      "strongs": "G34400",
      "morph": "Gr,D,,,,,,,,,"
    },
    {
      "word": "ἀλλ’",
      "lemma": "ἀλλά",
      "strongs": "G02350",
      "morph": "Gr,CO,,,,,,,,"
    },
    {
      "word": "ἐν",
      "lemma": "ἐν",
      "strongs": "G17220",
      "morph": "Gr,P,,,,,D,,,"
    },
    {
      "word": "τῷ",
      "lemma": "ὁ",
      "strongs": "G35880",
      "morph": "Gr,EA,,,,DNS,"
    },
    {
      "word": "ὕδατι",
      "lemma": "ὕδωρ",
      "strongs": "G52040",
      "morph": "Gr,N,,,,,DNS,"
    },
    {
      "word": "καὶ",
      "lemma": "καί",
      "strongs": "G25320",
      "morph": "Gr,CC,,,,,,,,"
    },
    {
      "word": "ἐν",
      "lemma": "ἐν",
      "strongs": "G17220",
      "morph": "Gr,P,,,,,D,,,"
    },
    {
      "word": "τῷ",
      "lemma": "ὁ",
      "strongs": "G35880",
      "morph": "Gr,EA,,,,DNS,"
    },
    {
      "word": "αἵματι",
      "lemma": "αἷμα",
      "strongs": "G01290",
      "morph": "Gr,N,,,,,DNS,"
    },
    {
      "word": "καὶ",
      "lemma": "καί",
      "strongs": "G25320",
      "morph": "Gr,CC,,,,,,,,"
    },
    {
      "word": "τὸ",
      "lemma": "ὁ",
      "strongs": "G35880",
      "morph": "Gr,EA,,,,NNS,"
    },
    {
      "word": "Πνεῦμά",
      "lemma": "πνεῦμα",
      "strongs": "G41510",
      "morph": "Gr,N,,,,,NNS,"
    },
    {
      "word": "ἐστιν",
      "lemma": "εἰμί",
      "strongs": "G15100",
      "morph": "Gr,V,IPA3,,S,"
    },
    {
      "word": "τὸ",
      "lemma": "ὁ",
      "strongs": "G35880",
      "morph": "Gr,RD,,,,NNS,"
    },
    {
      "word": "μαρτυροῦν",
      "lemma": "μαρτυρέω",
      "strongs": "G31400",
      "morph": "Gr,V,PPA,NNS,"
    },
    {
      "word": "ὅτι",
      "lemma": "ὅτι",
      "strongs": "G37540",
      "morph": "Gr,CS,,,,,,,,"
    },
    {
      "word": "τὸ",
      "lemma": "ὁ",
      "strongs": "G35880",
      "morph": "Gr,EA,,,,NNS,"
    },
    {
      "word": "Πνεῦμά",
      "lemma": "πνεῦμα",
      "strongs": "G41510",
      "morph": "Gr,N,,,,,NNS,"
    },
    {
      "word": "ἐστιν",
      "lemma": "εἰμί",
      "strongs": "G15100",
      "morph": "Gr,V,IPA3,,S,"
    },
    {
      "word": "ἡ",
      "lemma": "ὁ",
      "strongs": "G35880",
      "morph": "Gr,EA,,,,NFS,"
    },
    {
      "word": "ἀλήθεια",
      "lemma": "ἀλήθεια",
      "strongs": "G02250",
      "morph": "Gr,N,,,,,NFS,"
    }
  ],
  "7": [
    {
      "word": "ὅτι",
      "lemma": "ὅτι",
      "strongs": "G37540",
      "morph": "Gr,CS,,,,,,,,"
    },
    {
      "word": "τρεῖς",
      "lemma": "τρεῖς",
      "strongs": "G51400",
      "morph": "Gr,NP,,,,NMP,"
    },
    {
      "word": "εἰσιν",
      "lemma": "εἰμί",
      "strongs": "G15100",
      "morph": "Gr,V,IPA3,,P,"
    },
    {
      "word": "οἱ",
      "lemma": "ὁ",
      "strongs": "G35880",
      "morph": "Gr,RD,,,,NMP,"
    },
    {
      "word": "μαρτυροῦντες",
      "lemma": "μαρτυρέω",
      "strongs": "G31400",
      "morph": "Gr,V,PPA,NMP,"
    }
  ],
  "8": [
    {
      "word": "τὸ",
      "lemma": "ὁ",
      "strongs": "G35880",
      "morph": "Gr,EA,,,,NNS,"
    },
    {
      "word": "Πνεῦμα",
      "lemma": "πνεῦμα",
      "strongs": "G41510",
      "morph": "Gr,N,,,,,NNS,"
    },
    {
      "word": "καὶ",
      "lemma": "καί",
      "strongs": "G25320",
      "morph": "Gr,CC,,,,,,,,"
    },
    {
      "word": "τὸ",
      "lemma": "ὁ",
      "strongs": "G35880",
      "morph": "Gr,EA,,,,NNS,"
    },
    {
      "word": "ὕδωρ",
      "lemma": "ὕδωρ",
      "strongs": "G52040",
      "morph": "Gr,N,,,,,NNS,"
    },
    {
      "word": "καὶ",
      "lemma": "καί",
      "strongs": "G25320",
      "morph": "Gr,CC,,,,,,,,"
    },
    {
      "word": "τὸ",
      "lemma": "ὁ",
      "strongs": "G35880",
      "morph": "Gr,EA,,,,NNS,"
    },
    {
      "word": "αἷμα",
      "lemma": "αἷμα",
      "strongs": "G01290",
      "morph": "Gr,N,,,,,NNS,"
    },
    {
      "word": "καὶ",
      "lemma": "καί",
      "strongs": "G25320",
      "morph": "Gr,CC,,,,,,,,"
    },
    {
      "word": "οἱ",
      "lemma": "ὁ",
      "strongs": "G35880",
      "morph": "Gr,EA,,,,NMP,"
    },
    {
      "word": "τρεῖς",
      "lemma": "τρεῖς",
      "strongs": "G51400",
      "morph": "Gr,NS,,,,NMP,"
    },
    {
      "word": "εἰς",
      "lemma": "εἰς",
      "strongs": "G15190",
      "morph": "Gr,P,,,,,A,,,"
    },
    {
      "word": "τὸ",
      "lemma": "ὁ",
      "strongs": "G35880",
      "morph": "Gr,EA,,,,ANS,"
    },
    {
      "word": "ἕν",
      "lemma": "εἷς",
      "strongs": "G15200",
      "morph": "Gr,NS,,,,ANS,"
    },
    {
      "word": "εἰσιν",
      "lemma": "εἰμί",
      "strongs": "G15100",
      "morph": "Gr,V,IPA3,,P,"
    }
  ],
  "9": [
    {
      "word": "εἰ",
      "lemma": "εἰ",
      "strongs": "G14870",
      "morph": "Gr,CS,,,,,,,,"
    },
    {
      "word": "τὴν",
      "lemma": "ὁ",
      "strongs": "G35880",
      "morph": "Gr,EA,,,,AFS,"
    },
    {
      "word": "μαρτυρίαν",
      "lemma": "μαρτυρία",
      "strongs": "G31410",
      "morph": "Gr,N,,,,,AFS,"
    },
    {
      "word": "τῶν",
      "lemma": "ὁ",
      "strongs": "G35880",
      "morph": "Gr,EA,,,,GMP,"
    },
    {
      "word": "ἀνθρώπων",
      "lemma": "ἄνθρωπος",
      "strongs": "G04440",
      "morph": "Gr,N,,,,,GMP,"
    },
    {
      "word": "λαμβάνομεν",
      "lemma": "λαμβάνω",
      "strongs": "G29830",
      "morph": "Gr,V,IPA1,,P,"
    },
    {
      "word": "ἡ",
      "lemma": "ὁ",
      "strongs": "G35880",
      "morph": "Gr,EA,,,,NFS,"
    },
    {
      "word": "μαρτυρία",
      "lemma": "μαρτυρία",
      "strongs": "G31410",
      "morph": "Gr,N,,,,,NFS,"
    },
    {
      "word": "τοῦ",
      "lemma": "ὁ",
      "strongs": "G35880",
      "morph": "Gr,EA,,,,GMS,"
    },
    {
      "word": "Θεοῦ",
      "lemma": "θεός",
      "strongs": "G23160",
      "morph": "Gr,N,,,,,GMS,"
    },
    {
      "word": "μείζων",
      "lemma": "μείζων",
      "strongs": "G31870",
      "morph": "Gr,NP,,,,NFSC"
    },
    {
      "word": "ἐστίν",
      "lemma": "εἰμί",
      "strongs": "G15100",
      "morph": "Gr,V,IPA3,,S,"
    },
    {
      "word": "ὅτι",
      "lemma": "ὅτι",
      "strongs": "G37540",
      "morph": "Gr,CS,,,,,,,,"
    },
    {
      "word": "αὕτη",
      "lemma": "οὗτος",
      "strongs": "G37780",
      "morph": "Gr,RD,,,,NFS,"
    },
    {
      "word": "ἐστὶν",
      "lemma": "εἰμί",
      "strongs": "G15100",
      "morph": "Gr,V,IPA3,,S,"
    },
    {
      "word": "ἡ",
      "lemma": "ὁ",
      "strongs": "G35880",
      "morph": "Gr,EA,,,,NFS,"
    },
    {
      "word": "μαρτυρία",
      "lemma": "μαρτυρία",
      "strongs": "G31410",
      "morph": "Gr,N,,,,,NFS,"
    },
    {
      "word": "τοῦ",
      "lemma": "ὁ",
      "strongs": "G35880",
      "morph": "Gr,EA,,,,GMS,"
    },
    {
      "word": "Θεοῦ",
      "lemma": "θεός",
      "strongs": "G23160",
      "morph": "Gr,N,,,,,GMS,"
    },
    {
      "word": "ὅτι",
      "lemma": "ὅτι",
      "strongs": "G37540",
      "morph": "Gr,CS,,,,,,,,"
    },
    {
      "word": "μεμαρτύρηκεν",
      "lemma": "μαρτυρέω",
      "strongs": "G31400",
      "morph": "Gr,V,IEA3,,S,"
    },
    {
      "word": "περὶ",
      "lemma": "περί",
      "strongs": "G40120",
      "morph": "Gr,P,,,,,G,,,"
    },
    {
      "word": "τοῦ",
      "lemma": "ὁ",
      "strongs": "G35880",
      "morph": "Gr,EA,,,,GMS,"
    },
    {
      "word": "Υἱοῦ",
      "lemma": "υἱός",
      "strongs": "G52070",
      "morph": "Gr,N,,,,,GMS,"
    },
    {
      "word": "αὐτοῦ",
      "lemma": "αὐτός",
      "strongs": "G08460",
      "morph": "Gr,RP,,,3GMS,"
    }
  ],
  "10": [
    {
      "word": "ὁ",
      "lemma": "ὁ",
      "strongs": "G35880",
      "morph": "Gr,RD,,,,NMS,"
    },
    {
      "word": "πιστεύων",
      "lemma": "πιστεύω",
      "strongs": "G41000",
      "morph": "Gr,V,PPA,NMS,"
    },
    {
      "word": "εἰς",
      "lemma": "εἰς",
      "strongs": "G15190",
      "morph": "Gr,P,,,,,A,,,"
    },
    {
      "word": "τὸν",
      "lemma": "ὁ",
      "strongs": "G35880",
      "morph": "Gr,EA,,,,AMS,"
    },
    {
      "word": "Υἱὸν",
      "lemma": "υἱός",
      "strongs": "G52070",
      "morph": "Gr,N,,,,,AMS,"
    },
    {
      "word": "τοῦ",
      "lemma": "ὁ",
      "strongs": "G35880",
      "morph": "Gr,EA,,,,GMS,"
    },
    {
      "word": "Θεοῦ",
      "lemma": "θεός",
      "strongs": "G23160",
      "morph": "Gr,N,,,,,GMS,"
    },
    {
      "word": "ἔχει",
      "lemma": "ἔχω",
      "strongs": "G21920",
      "morph": "Gr,V,IPA3,,S,"
    },
    {
      "word": "τὴν",
      "lemma": "ὁ",
      "strongs": "G35880",
      "morph": "Gr,EA,,,,AFS,"
    },
    {
      "word": "μαρτυρίαν",
      "lemma": "μαρτυρία",
      "strongs": "G31410",
      "morph": "Gr,N,,,,,AFS,"
    },
    {
      "word": "ἐν",
      "lemma": "ἐν",
      "strongs": "G17220",
      "morph": "Gr,P,,,,,D,,,"
    },
    {
      "word": "αὑτῷ",
      "lemma": "αὐτός",
      "strongs": "G08460",
      "morph": "Gr,RE,,,3DMS,"
    },
    {
      "word": "ὁ",
      "lemma": "ὁ",
      "strongs": "G35880",
      "morph": "Gr,RD,,,,NMS,"
    },
    {
      "word": "μὴ",
      "lemma": "μή",
      "strongs": "G33610",
      "morph": "Gr,D,,,,,,,,,"
    },
    {
      "word": "πιστεύων",
      "lemma": "πιστεύω",
      "strongs": "G41000",
      "morph": "Gr,V,PPA,NMS,"
    },
    {
      "word": "τῷ",
      "lemma": "ὁ",
      "strongs": "G35880",
      "morph": "Gr,EA,,,,DMS,"
    },
    {
      "word": "Θεῷ",
      "lemma": "θεός",
      "strongs": "G23160",
      "morph": "Gr,N,,,,,DMS,"
    },
    {
      "word": "ψεύστην",
      "lemma": "ψεύστης",
      "strongs": "G55830",
      "morph": "Gr,N,,,,,AMS,"
    },
    {
      "word": "πεποίηκεν",
      "lemma": "ποιέω",
      "strongs": "G41600",
      "morph": "Gr,V,IEA3,,S,"
    },
    {
      "word": "αὐτόν",
      "lemma": "αὐτός",
      "strongs": "G08460",
      "morph": "Gr,RP,,,3AMS,"
    },
    {
      "word": "ὅτι",
      "lemma": "ὅτι",
      "strongs": "G37540",
      "morph": "Gr,CS,,,,,,,,"
    },
    {
      "word": "οὐ",
      "lemma": "οὐ",
      "strongs": "G37560",
      "morph": "Gr,D,,,,,,,,,"
    },
    {
      "word": "πεπίστευκεν",
      "lemma": "πιστεύω",
      "strongs": "G41000",
      "morph": "Gr,V,IEA3,,S,"
    },
    {
      "word": "εἰς",
      "lemma": "εἰς",
      "strongs": "G15190",
      "morph": "Gr,P,,,,,A,,,"
    },
    {
      "word": "τὴν",
      "lemma": "ὁ",
      "strongs": "G35880",
      "morph": "Gr,EA,,,,AFS,"
    },
    {
      "word": "μαρτυρίαν",
      "lemma": "μαρτυρία",
      "strongs": "G31410",
      "morph": "Gr,N,,,,,AFS,"
    },
    {
      "word": "ἣν",
      "lemma": "ὅς",
      "strongs": "G37390",
      "morph": "Gr,RD,,,,AFS,"
    },
    {
      "word": "μεμαρτύρηκεν",
      "lemma": "μαρτυρέω",
      "strongs": "G31400",
      "morph": "Gr,V,IEA3,,S,"
    },
    {
      "word": "ὁ",
      "lemma": "ὁ",
      "strongs": "G35880",
      "morph": "Gr,EA,,,,NMS,"
    },
    {
      "word": "Θεὸς",
      "lemma": "θεός",
      "strongs": "G23160",
      "morph": "Gr,N,,,,,NMS,"
    },
    {
      "word": "περὶ",
      "lemma": "περί",
      "strongs": "G40120",
      "morph": "Gr,P,,,,,G,,,"
    },
    {
      "word": "τοῦ",
      "lemma": "ὁ",
      "strongs": "G35880",
      "morph": "Gr,EA,,,,GMS,"
    },
    {
      "word": "Υἱοῦ",
      "lemma": "υἱός",
      "strongs": "G52070",
      "morph": "Gr,N,,,,,GMS,"
    },
    {
      "word": "αὐτοῦ",
      "lemma": "αὐτός",
      "strongs": "G08460",
      "morph": "Gr,RP,,,3GMS,"
    }
  ],
  "11": [
    {
      "word": "καὶ",
      "lemma": "καί",
      "strongs": "G25320",
      "morph": "Gr,CC,,,,,,,,"
    },
    {
      "word": "αὕτη",
      "lemma": "οὗτος",
      "strongs": "G37780",
      "morph": "Gr,RD,,,,NFS,"
    },
    {
      "word": "ἐστὶν",
      "lemma": "εἰμί",
      "strongs": "G15100",
      "morph": "Gr,V,IPA3,,S,"
    },
    {
      "word": "ἡ",
      "lemma": "ὁ",
      "strongs": "G35880",
      "morph": "Gr,EA,,,,NFS,"
    },
    {
      "word": "μαρτυρία",
      "lemma": "μαρτυρία",
      "strongs": "G31410",
      "morph": "Gr,N,,,,,NFS,"
    },
    {
      "word": "ὅτι",
      "lemma": "ὅτι",
      "strongs": "G37540",
      "morph": "Gr,CS,,,,,,,,"
    },
    {
      "word": "ζωὴν",
      "lemma": "ζωή",
      "strongs": "G22220",
      "morph": "Gr,N,,,,,AFS,"
    },
    {
      "word": "αἰώνιον",
      "lemma": "αἰώνιος",
      "strongs": "G01660",
      "morph": "Gr,AA,,,,AFS,"
    },
    {
      "word": "ἔδωκεν",
      "lemma": "δίδωμι",
      "strongs": "G13250",
      "morph": "Gr,V,IAA3,,S,"
    },
    {
      "word": "ἡμῖν",
      "lemma": "ἐγώ",
      "strongs": "G14730",
      "morph": "Gr,RP,,,1D,P,"
    },
    {
      "word": "ὁ",
      "lemma": "ὁ",
      "strongs": "G35880",
      "morph": "Gr,EA,,,,NMS,"
    },
    {
      "word": "Θεὸς",
      "lemma": "θεός",
      "strongs": "G23160",
      "morph": "Gr,N,,,,,NMS,"
    },
    {
      "word": "καὶ",
      "lemma": "καί",
      "strongs": "G25320",
      "morph": "Gr,CC,,,,,,,,"
    },
    {
      "word": "αὕτη",
      "lemma": "οὗτος",
      "strongs": "G37780",
      "morph": "Gr,ED,,,,NFS,"
    },
    {
      "word": "ἡ",
      "lemma": "ὁ",
      "strongs": "G35880",
      "morph": "Gr,EA,,,,NFS,"
    },
    {
      "word": "ζωὴ",
      "lemma": "ζωή",
      "strongs": "G22220",
      "morph": "Gr,N,,,,,NFS,"
    },
    {
      "word": "ἐν",
      "lemma": "ἐν",
      "strongs": "G17220",
      "morph": "Gr,P,,,,,D,,,"
    },
    {
      "word": "τῷ",
      "lemma": "ὁ",
      "strongs": "G35880",
      "morph": "Gr,EA,,,,DMS,"
    },
    {
      "word": "Υἱῷ",
      "lemma": "υἱός",
      "strongs": "G52070",
      "morph": "Gr,N,,,,,DMS,"
    },
    {
      "word": "αὐτοῦ",
      "lemma": "αὐτός",
      "strongs": "G08460",
      "morph": "Gr,RP,,,3GMS,"
    },
    {
      "word": "ἐστιν",
      "lemma": "εἰμί",
      "strongs": "G15100",
      "morph": "Gr,V,IPA3,,S,"
    }
  ],
  "12": [
    {
      "word": "ὁ",
      "lemma": "ὁ",
      "strongs": "G35880",
      "morph": "Gr,RD,,,,NMS,"
    },
    {
      "word": "ἔχων",
      "lemma": "ἔχω",
      "strongs": "G21920",
      "morph": "Gr,V,PPA,NMS,"
    },
    {
      "word": "τὸν",
      "lemma": "ὁ",
      "strongs": "G35880",
      "morph": "Gr,EA,,,,AMS,"
    },
    {
      "word": "Υἱὸν",
      "lemma": "υἱός",
      "strongs": "G52070",
      "morph": "Gr,N,,,,,AMS,"
    },
    {
      "word": "ἔχει",
      "lemma": "ἔχω",
      "strongs": "G21920",
      "morph": "Gr,V,IPA3,,S,"
    },
    {
      "word": "τὴν",
      "lemma": "ὁ",
      "strongs": "G35880",
      "morph": "Gr,EA,,,,AFS,"
    },
    {
      "word": "ζωήν",
      "lemma": "ζωή",
      "strongs": "G22220",
      "morph": "Gr,N,,,,,AFS,"
    },
    {
      "word": "ὁ",
      "lemma": "ὁ",
      "strongs": "G35880",
      "morph": "Gr,RD,,,,NMS,"
    },
    {
      "word": "μὴ",
      "lemma": "μή",
      "strongs": "G33610",
      "morph": "Gr,D,,,,,,,,,"
    },
    {
      "word": "ἔχων",
      "lemma": "ἔχω",
      "strongs": "G21920",
      "morph": "Gr,V,PPA,NMS,"
    },
    {
      "word": "τὸν",
      "lemma": "ὁ",
      "strongs": "G35880",
      "morph": "Gr,EA,,,,AMS,"
    },
    {
      "word": "Υἱὸν",
      "lemma": "υἱός",
      "strongs": "G52070",
      "morph": "Gr,N,,,,,AMS,"
    },
    {
      "word": "τοῦ",
      "lemma": "ὁ",
      "strongs": "G35880",
      "morph": "Gr,EA,,,,GMS,"
    },
    {
      "word": "Θεοῦ",
      "lemma": "θεός",
      "strongs": "G23160",
      "morph": "Gr,N,,,,,GMS,"
    },
    {
      "word": "τὴν",
      "lemma": "ὁ",
      "strongs": "G35880",
      "morph": "Gr,EA,,,,AFS,"
    },
    {
      "word": "ζωὴν",
      "lemma": "ζωή",
      "strongs": "G22220",
      "morph": "Gr,N,,,,,AFS,"
    },
    {
      "word": "οὐκ",
      "lemma": "οὐ",
      "strongs": "G37560",
      "morph": "Gr,D,,,,,,,,,"
    },
    {
      "word": "ἔχει",
      "lemma": "ἔχω",
      "strongs": "G21920",
      "morph": "Gr,V,IPA3,,S,"
    }
  ],
  "13": [
    {
      "word": "ταῦτα",
      "lemma": "οὗτος",
      "strongs": "G37780",
      "morph": "Gr,RD,,,,ANP,"
    },
    {
      "word": "ἔγραψα",
      "lemma": "γράφω",
      "strongs": "G11250",
      "morph": "Gr,V,IAA1,,S,"
    },
    {
      "word": "ὑμῖν",
      "lemma": "σύ",
      "strongs": "G47710",
      "morph": "Gr,RP,,,2D,P,"
    },
    {
      "word": "ἵνα",
      "lemma": "ἵνα",
      "strongs": "G24430",
      "morph": "Gr,CS,,,,,,,,"
    },
    {
      "word": "εἰδῆτε",
      "lemma": "εἴδω",
      "strongs": "G14920",
      "morph": "Gr,V,SEA2,,P,"
    },
    {
      "word": "ὅτι",
      "lemma": "ὅτι",
      "strongs": "G37540",
      "morph": "Gr,CS,,,,,,,,"
    },
    {
      "word": "ζωὴν",
      "lemma": "ζωή",
      "strongs": "G22220",
      "morph": "Gr,N,,,,,AFS,"
    },
    {
      "word": "ἔχετε",
      "lemma": "ἔχω",
      "strongs": "G21920",
      "morph": "Gr,V,IPA2,,P,"
    },
    {
      "word": "αἰώνιον",
      "lemma": "αἰώνιος",
      "strongs": "G01660",
      "morph": "Gr,NS,,,,AFS,"
    },
    {
      "word": "τοῖς",
      "lemma": "ὁ",
      "strongs": "G35880",
      "morph": "Gr,RD,,,,DMP,"
    },
    {
      "word": "πιστεύουσιν",
      "lemma": "πιστεύω",
      "strongs": "G41000",
      "morph": "Gr,V,PPA,DMP,"
    },
    {
      "word": "εἰς",
      "lemma": "εἰς",
      "strongs": "G15190",
      "morph": "Gr,P,,,,,A,,,"
    },
    {
      "word": "τὸ",
      "lemma": "ὁ",
      "strongs": "G35880",
      "morph": "Gr,EA,,,,ANS,"
    },
    {
      "word": "ὄνομα",
      "lemma": "ὄνομα",
      "strongs": "G36860",
      "morph": "Gr,N,,,,,ANS,"
    },
    {
      "word": "τοῦ",
      "lemma": "ὁ",
      "strongs": "G35880",
      "morph": "Gr,EA,,,,GMS,"
    },
    {
      "word": "Υἱοῦ",
      "lemma": "υἱός",
      "strongs": "G52070",
      "morph": "Gr,N,,,,,GMS,"
    },
    {
      "word": "τοῦ",
      "lemma": "ὁ",
      "strongs": "G35880",
      "morph": "Gr,EA,,,,GMS,"
    },
    {
      "word": "Θεοῦ",
      "lemma": "θεός",
      "strongs": "G23160",
      "morph": "Gr,N,,,,,GMS,"
    }
  ],
  "14": [
    {
      "word": "καὶ",
      "lemma": "καί",
      "strongs": "G25320",
      "morph": "Gr,CC,,,,,,,,"
    },
    {
      "word": "αὕτη",
      "lemma": "οὗτος",
      "strongs": "G37780",
      "morph": "Gr,RD,,,,NFS,"
    },
    {
      "word": "ἐστὶν",
      "lemma": "εἰμί",
      "strongs": "G15100",
      "morph": "Gr,V,IPA3,,S,"
    },
    {
      "word": "ἡ",
      "lemma": "ὁ",
      "strongs": "G35880",
      "morph": "Gr,EA,,,,NFS,"
    },
    {
      "word": "παρρησία",
      "lemma": "παρρησία",
      "strongs": "G39540",
      "morph": "Gr,N,,,,,NFS,"
    },
    {
      "word": "ἣν",
      "lemma": "ὅς",
      "strongs": "G37390",
      "morph": "Gr,RD,,,,AFS,"
    },
    {
      "word": "ἔχομεν",
      "lemma": "ἔχω",
      "strongs": "G21920",
      "morph": "Gr,V,IPA1,,P,"
    },
    {
      "word": "πρὸς",
      "lemma": "πρός",
      "strongs": "G43140",
      "morph": "Gr,P,,,,,A,,,"
    },
    {
      "word": "αὐτόν",
      "lemma": "αὐτός",
      "strongs": "G08460",
      "morph": "Gr,RP,,,3AMS,"
    },
    {
      "word": "ὅτι",
      "lemma": "ὅτι",
      "strongs": "G37540",
      "morph": "Gr,CS,,,,,,,,"
    },
    {
      "word": "ἐάν",
      "lemma": "ἐάν",
      "strongs": "G14370",
      "morph": "Gr,CS,,,,,,,,"
    },
    {
      "word": "τι",
      "lemma": "τις",
      "strongs": "G51000",
      "morph": "Gr,RI,,,,ANS,"
    },
    {
      "word": "αἰτώμεθα",
      "lemma": "αἰτέω",
      "strongs": "G01540",
      "morph": "Gr,V,SPM1,,P,"
    },
    {
      "word": "κατὰ",
      "lemma": "κατά",
      "strongs": "G25960",
      "morph": "Gr,P,,,,,A,,,"
    },
    {
      "word": "τὸ",
      "lemma": "ὁ",
      "strongs": "G35880",
      "morph": "Gr,EA,,,,ANS,"
    },
    {
      "word": "θέλημα",
      "lemma": "θέλημα",
      "strongs": "G23070",
      "morph": "Gr,N,,,,,ANS,"
    },
    {
      "word": "αὐτοῦ",
      "lemma": "αὐτός",
      "strongs": "G08460",
      "morph": "Gr,RP,,,3GMS,"
    },
    {
      "word": "ἀκούει",
      "lemma": "ἀκούω",
      "strongs": "G01910",
      "morph": "Gr,V,IPA3,,S,"
    },
    {
      "word": "ἡμῶν",
      "lemma": "ἐγώ",
      "strongs": "G14730",
      "morph": "Gr,RP,,,1G,P,"
    }
  ],
  "15": [
    {
      "word": "καὶ",
      "lemma": "καί",
      "strongs": "G25320",
      "morph": "Gr,CC,,,,,,,,"
    },
    {
      "word": "ἐὰν",
      "lemma": "ἐάν",
      "strongs": "G14370",
      "morph": "Gr,CS,,,,,,,,"
    },
    {
      "word": "οἴδαμεν",
      "lemma": "οἶδα",
      "strongs": "G14920",
      "morph": "Gr,V,IEA1,,P,"
    },
    {
      "word": "ὅτι",
      "lemma": "ὅτι",
      "strongs": "G37540",
      "morph": "Gr,CS,,,,,,,,"
    },
    {
      "word": "ἀκούει",
      "lemma": "ἀκούω",
      "strongs": "G01910",
      "morph": "Gr,V,IPA3,,S,"
    },
    {
      "word": "ἡμῶν",
      "lemma": "ἐγώ",
      "strongs": "G14730",
      "morph": "Gr,RP,,,1G,P,"
    },
    {
      "word": "ὃ",
      "lemma": "ὅς",
      "strongs": "G37390",
      "morph": "Gr,RR,,,,ANS,"
    },
    {
      "word": "ἂν",
      "lemma": "ἄν",
      "strongs": "G03020",
      "morph": "Gr,T,,,,,,,,,"
    },
    {
      "word": "αἰτώμεθα",
      "lemma": "αἰτέω",
      "strongs": "G01540",
      "morph": "Gr,V,SPM1,,P,"
    },
    {
      "word": "οἴδαμεν",
      "lemma": "οἶδα",
      "strongs": "G14920",
      "morph": "Gr,V,IEA1,,P,"
    },
    {
      "word": "ὅτι",
      "lemma": "ὅτι",
      "strongs": "G37540",
      "morph": "Gr,CS,,,,,,,,"
    },
    {
      "word": "ἔχομεν",
      "lemma": "ἔχω",
      "strongs": "G21920",
      "morph": "Gr,V,IPA1,,P,"
    },
    {
      "word": "τὰ",
      "lemma": "ὁ",
      "strongs": "G35880",
      "morph": "Gr,EA,,,,ANP,"
    },
    {
      "word": "αἰτήματα",
      "lemma": "αἴτημα",
      "strongs": "G01550",
      "morph": "Gr,N,,,,,ANP,"
    },
    {
      "word": "ἃ",
      "lemma": "ὅς",
      "strongs": "G37390",
      "morph": "Gr,RD,,,,ANP,"
    },
    {
      "word": "ᾐτήκαμεν",
      "lemma": "αἰτέω",
      "strongs": "G01540",
      "morph": "Gr,V,IEA1,,P,"
    },
    {
      "word": "ἀπ’",
      "lemma": "ἀπό",
      "strongs": "G05750",
      "morph": "Gr,P,,,,,G,,,"
    },
    {
      "word": "αὐτοῦ",
      "lemma": "αὐτός",
      "strongs": "G08460",
      "morph": "Gr,RP,,,3GMS,"
    }
  ],
  "16": [
    {
      "word": "ἐάν",
      "lemma": "ἐάν",
      "strongs": "G14370",
      "morph": "Gr,CS,,,,,,,,"
    },
    {
      "word": "τις",
      "lemma": "τις",
      "strongs": "G51000",
      "morph": "Gr,RI,,,,NMS,"
    },
    {
      "word": "ἴδῃ",
      "lemma": "ὁράω",
      "strongs": "G37080",
      "morph": "Gr,V,SAA3,,S,"
    },
    {
      "word": "τὸν",
      "lemma": "ὁ",
      "strongs": "G35880",
      "morph": "Gr,EA,,,,AMS,"
    },
    {
      "word": "ἀδελφὸν",
      "lemma": "ἀδελφός",
      "strongs": "G00800",
      "morph": "Gr,N,,,,,AMS,"
    },
    {
      "word": "αὐτοῦ",
      "lemma": "αὐτός",
      "strongs": "G08460",
      "morph": "Gr,RP,,,3GMS,"
    },
    {
      "word": "ἁμαρτάνοντα",
      "lemma": "ἁμαρτάνω",
      "strongs": "G02640",
      "morph": "Gr,V,PPA,AMS,"
    },
    {
      "word": "ἁμαρτίαν",
      "lemma": "ἁμαρτία",
      "strongs": "G02660",
      "morph": "Gr,N,,,,,AFS,"
    },
    {
      "word": "μὴ",
      "lemma": "μή",
      "strongs": "G33610",
      "morph": "Gr,D,,,,,,,,,"
    },
    {
      "word": "πρὸς",
      "lemma": "πρός",
      "strongs": "G43140",
      "morph": "Gr,P,,,,,A,,,"
    },
    {
      "word": "θάνατον",
      "lemma": "θάνατος",
      "strongs": "G22880",
      "morph": "Gr,N,,,,,AMS,"
    },
    {
      "word": "αἰτήσει",
      "lemma": "αἰτέω",
      "strongs": "G01540",
      "morph": "Gr,V,IFA3,,S,"
    },
    {
      "word": "καὶ",
      "lemma": "καί",
      "strongs": "G25320",
      "morph": "Gr,CC,,,,,,,,"
    },
    {
      "word": "δώσει",
      "lemma": "δίδωμι",
      "strongs": "G13250",
      "morph": "Gr,V,IFA3,,S,"
    },
    {
      "word": "αὐτῷ",
      "lemma": "αὐτός",
      "strongs": "G08460",
      "morph": "Gr,RP,,,3DMS,"
    },
    {
      "word": "ζωήν",
      "lemma": "ζωή",
      "strongs": "G22220",
      "morph": "Gr,N,,,,,AFS,"
    },
    {
      "word": "τοῖς",
      "lemma": "ὁ",
      "strongs": "G35880",
      "morph": "Gr,RD,,,,DMP,"
    },
    {
      "word": "ἁμαρτάνουσιν",
      "lemma": "ἁμαρτάνω",
      "strongs": "G02640",
      "morph": "Gr,V,PPA,DMP,"
    },
    {
      "word": "μὴ",
      "lemma": "μή",
      "strongs": "G33610",
      "morph": "Gr,D,,,,,,,,,"
    },
    {
      "word": "πρὸς",
      "lemma": "πρός",
      "strongs": "G43140",
      "morph": "Gr,P,,,,,A,,,"
    },
    {
      "word": "θάνατον",
      "lemma": "θάνατος",
      "strongs": "G22880",
      "morph": "Gr,N,,,,,AMS,"
    },
    {
      "word": "ἔστιν",
      "lemma": "εἰμί",
      "strongs": "G15100",
      "morph": "Gr,V,IPA3,,S,"
    },
    {
      "word": "ἁμαρτία",
      "lemma": "ἁμαρτία",
      "strongs": "G02660",
      "morph": "Gr,N,,,,,NFS,"
    },
    {
      "word": "πρὸς",
      "lemma": "πρός",
      "strongs": "G43140",
      "morph": "Gr,P,,,,,A,,,"
    },
    {
      "word": "θάνατον",
      "lemma": "θάνατος",
      "strongs": "G22880",
      "morph": "Gr,N,,,,,AMS,"
    },
    {
      "word": "οὐ",
      "lemma": "οὐ",
      "strongs": "G37560",
      "morph": "Gr,D,,,,,,,,,"
    },
    {
      "word": "περὶ",
      "lemma": "περί",
      "strongs": "G40120",
      "morph": "Gr,P,,,,,G,,,"
    },
    {
      "word": "ἐκείνης",
      "lemma": "ἐκεῖνος",
      "strongs": "G15650",
      "morph": "Gr,RD,,,,GFS,"
    },
    {
      "word": "λέγω",
      "lemma": "λέγω",
      "strongs": "G30040",
      "morph": "Gr,V,IPA1,,S,"
    },
    {
      "word": "ἵνα",
      "lemma": "ἵνα",
      "strongs": "G24430",
      "morph": "Gr,CS,,,,,,,,"
    },
    {
      "word": "ἐρωτήσῃ",
      "lemma": "ἐρωτάω",
      "strongs": "G20650",
      "morph": "Gr,V,SAA3,,S,"
    }
  ],
  "17": [
    {
      "word": "πᾶσα",
      "lemma": "πᾶς",
      "strongs": "G39560",
      "morph": "Gr,EQ,,,,NFS,"
    },
    {
      "word": "ἀδικία",
      "lemma": "ἀδικία",
      "strongs": "G00930",
      "morph": "Gr,N,,,,,NFS,"
    },
    {
      "word": "ἁμαρτία",
      "lemma": "ἁμαρτία",
      "strongs": "G02660",
      "morph": "Gr,N,,,,,NFS,"
    },
    {
      "word": "ἐστίν",
      "lemma": "εἰμί",
      "strongs": "G15100",
      "morph": "Gr,V,IPA3,,S,"
    },
    {
      "word": "καὶ",
      "lemma": "καί",
      "strongs": "G25320",
      "morph": "Gr,CC,,,,,,,,"
    },
    {
      "word": "ἔστιν",
      "lemma": "εἰμί",
      "strongs": "G15100",
      "morph": "Gr,V,IPA3,,S,"
    },
    {
      "word": "ἁμαρτία",
      "lemma": "ἁμαρτία",
      "strongs": "G02660",
      "morph": "Gr,N,,,,,NFS,"
    },
    {
      "word": "οὐ",
      "lemma": "οὐ",
      "strongs": "G37560",
      "morph": "Gr,D,,,,,,,,,"
    },
    {
      "word": "πρὸς",
      "lemma": "πρός",
      "strongs": "G43140",
      "morph": "Gr,P,,,,,A,,,"
    },
    {
      "word": "θάνατον",
      "lemma": "θάνατος",
      "strongs": "G22880",
      "morph": "Gr,N,,,,,AMS,"
    }
  ],
  "18": [
    {
      "word": "οἴδαμεν",
      "lemma": "οἶδα",
      "strongs": "G14920",
      "morph": "Gr,V,IEA1,,P,"
    },
    {
      "word": "ὅτι",
      "lemma": "ὅτι",
      "strongs": "G37540",
      "morph": "Gr,CS,,,,,,,,"
    },
    {
      "word": "πᾶς",
      "lemma": "πᾶς",
      "strongs": "G39560",
      "morph": "Gr,RI,,,,NMS,"
    },
    {
      "word": "ὁ",
      "lemma": "ὁ",
      "strongs": "G35880",
      "morph": "Gr,RD,,,,NMS,"
    },
    {
      "word": "γεγεννημένος",
      "lemma": "γεννάω",
      "strongs": "G10800",
      "morph": "Gr,V,PEP,NMS,"
    },
    {
      "word": "ἐκ",
      "lemma": "ἐκ",
      "strongs": "G15370",
      "morph": "Gr,P,,,,,G,,,"
    },
    {
      "word": "τοῦ",
      "lemma": "ὁ",
      "strongs": "G35880",
      "morph": "Gr,EA,,,,GMS,"
    },
    {
      "word": "Θεοῦ",
      "lemma": "θεός",
      "strongs": "G23160",
      "morph": "Gr,N,,,,,GMS,"
    },
    {
      "word": "οὐχ",
      "lemma": "οὐ",
      "strongs": "G37560",
      "morph": "Gr,D,,,,,,,,,"
    },
    {
      "word": "ἁμαρτάνει",
      "lemma": "ἁμαρτάνω",
      "strongs": "G02640",
      "morph": "Gr,V,IPA3,,S,"
    },
    {
      "word": "ἀλλ’",
      "lemma": "ἀλλά",
      "strongs": "G02350",
      "morph": "Gr,CC,,,,,,,,"
    },
    {
      "word": "ὁ",
      "lemma": "ὁ",
      "strongs": "G35880",
      "morph": "Gr,RD,,,,NMS,"
    },
    {
      "word": "γεννηθεὶς",
      "lemma": "γεννάω",
      "strongs": "G10800",
      "morph": "Gr,V,PAP,NMS,"
    },
    {
      "word": "ἐκ",
      "lemma": "ἐκ",
      "strongs": "G15370",
      "morph": "Gr,P,,,,,G,,,"
    },
    {
      "word": "τοῦ",
      "lemma": "ὁ",
      "strongs": "G35880",
      "morph": "Gr,EA,,,,GMS,"
    },
    {
      "word": "Θεοῦ",
      "lemma": "θεός",
      "strongs": "G23160",
      "morph": "Gr,N,,,,,GMS,"
    },
    {
      "word": "τηρεῖ",
      "lemma": "τηρέω",
      "strongs": "G50830",
      "morph": "Gr,V,IPA3,,S,"
    },
    {
      "word": "ἑαυτὸν",
      "lemma": "ἑαυτοῦ",
      "strongs": "G14380",
      "morph": "Gr,RE,,,3AMS,"
    },
    {
      "word": "καὶ",
      "lemma": "καί",
      "strongs": "G25320",
      "morph": "Gr,CC,,,,,,,,"
    },
    {
      "word": "ὁ",
      "lemma": "ὁ",
      "strongs": "G35880",
      "morph": "Gr,EA,,,,NMS,"
    },
    {
      "word": "πονηρὸς",
      "lemma": "πονηρός",
      "strongs": "G41900",
      "morph": "Gr,NS,,,,NMS,"
    },
    {
      "word": "οὐχ",
      "lemma": "οὐ",
      "strongs": "G37560",
      "morph": "Gr,D,,,,,,,,,"
    },
    {
      "word": "ἅπτεται",
      "lemma": "ἅπτω",
      "strongs": "G06810",
      "morph": "Gr,V,IPM3,,S,"
    },
    {
      "word": "αὐτοῦ",
      "lemma": "αὐτός",
      "strongs": "G08460",
      "morph": "Gr,RP,,,3GMS,"
    }
  ],
  "19": [
    {
      "word": "οἴδαμεν",
      "lemma": "οἶδα",
      "strongs": "G14920",
      "morph": "Gr,V,IEA1,,P,"
    },
    {
      "word": "ὅτι",
      "lemma": "ὅτι",
      "strongs": "G37540",
      "morph": "Gr,CS,,,,,,,,"
    },
    {
      "word": "ἐκ",
      "lemma": "ἐκ",
      "strongs": "G15370",
      "morph": "Gr,P,,,,,G,,,"
    },
    {
      "word": "τοῦ",
      "lemma": "ὁ",
      "strongs": "G35880",
      "morph": "Gr,EA,,,,GMS,"
    },
    {
      "word": "Θεοῦ",
      "lemma": "θεός",
      "strongs": "G23160",
      "morph": "Gr,N,,,,,GMS,"
    },
    {
      "word": "ἐσμεν",
      "lemma": "εἰμί",
      "strongs": "G15100",
      "morph": "Gr,V,IPA1,,P,"
    },
    {
      "word": "καὶ",
      "lemma": "καί",
      "strongs": "G25320",
      "morph": "Gr,CC,,,,,,,,"
    },
    {
      "word": "ὁ",
      "lemma": "ὁ",
      "strongs": "G35880",
      "morph": "Gr,EA,,,,NMS,"
    },
    {
      "word": "κόσμος",
      "lemma": "κόσμος",
      "strongs": "G28890",
      "morph": "Gr,N,,,,,NMS,"
    },
    {
      "word": "ὅλος",
      "lemma": "ὅλος",
      "strongs": "G36500",
      "morph": "Gr,EQ,,,,NMS,"
    },
    {
      "word": "ἐν",
      "lemma": "ἐν",
      "strongs": "G17220",
      "morph": "Gr,P,,,,,D,,,"
    },
    {
      "word": "τῷ",
      "lemma": "ὁ",
      "strongs": "G35880",
      "morph": "Gr,EA,,,,DMS,"
    },
    {
      "word": "πονηρῷ",
      "lemma": "πονηρός",
      "strongs": "G41900",
      "morph": "Gr,NS,,,,DMS,"
    },
    {
      "word": "κεῖται",
      "lemma": "κεῖμαι",
      "strongs": "G27490",
      "morph": "Gr,V,IPM3,,S,"
    }
  ],
  "20": [
    {
      "word": "οἴδαμεν",
      "lemma": "οἶδα",
      "strongs": "G14920",
      "morph": "Gr,V,IEA1,,P,"
    },
    {
      "word": "δὲ",
      "lemma": "δέ",
      "strongs": "G11610",
      "morph": "Gr,CC,,,,,,,,"
    },
    {
      "word": "ὅτι",
      "lemma": "ὅτι",
      "strongs": "G37540",
      "morph": "Gr,CS,,,,,,,,"
    },
    {
      "word": "ὁ",
      "lemma": "ὁ",
      "strongs": "G35880",
      "morph": "Gr,EA,,,,NMS,"
    },
    {
      "word": "Υἱὸς",
      "lemma": "υἱός",
      "strongs": "G52070",
      "morph": "Gr,N,,,,,NMS,"
    },
    {
      "word": "τοῦ",
      "lemma": "ὁ",
      "strongs": "G35880",
      "morph": "Gr,EA,,,,GMS,"
    },
    {
      "word": "Θεοῦ",
      "lemma": "θεός",
      "strongs": "G23160",
      "morph": "Gr,N,,,,,GMS,"
    },
    {
      "word": "ἥκει",
      "lemma": "ἥκω",
      "strongs": "G22400",
      "morph": "Gr,V,IPA3,,S,"
    },
    {
      "word": "καὶ",
      "lemma": "καί",
      "strongs": "G25320",
      "morph": "Gr,CC,,,,,,,,"
    },
    {
      "word": "δέδωκεν",
      "lemma": "δίδωμι",
      "strongs": "G13250",
      "morph": "Gr,V,IEA3,,S,"
    },
    {
      "word": "ἡμῖν",
      "lemma": "ἐγώ",
      "strongs": "G14730",
      "morph": "Gr,RP,,,1D,P,"
    },
    {
      "word": "διάνοιαν",
      "lemma": "διάνοια",
      "strongs": "G12710",
      "morph": "Gr,N,,,,,AFS,"
    },
    {
      "word": "ἵνα",
      "lemma": "ἵνα",
      "strongs": "G24430",
      "morph": "Gr,CS,,,,,,,,"
    },
    {
      "word": "γινώσκωμεν",
      "lemma": "γινώσκω",
      "strongs": "G10970",
      "morph": "Gr,V,SPA1,,P,"
    },
    {
      "word": "τὸν",
      "lemma": "ὁ",
      "strongs": "G35880",
      "morph": "Gr,EA,,,,AMS,"
    },
    {
      "word": "Ἀληθινόν",
      "lemma": "ἀληθινός",
      "strongs": "G02280",
      "morph": "Gr,NS,,,,AMS,"
    },
    {
      "word": "καὶ",
      "lemma": "καί",
      "strongs": "G25320",
      "morph": "Gr,CC,,,,,,,,"
    },
    {
      "word": "ἐσμὲν",
      "lemma": "εἰμί",
      "strongs": "G15100",
      "morph": "Gr,V,IPA1,,P,"
    },
    {
      "word": "ἐν",
      "lemma": "ἐν",
      "strongs": "G17220",
      "morph": "Gr,P,,,,,D,,,"
    },
    {
      "word": "τῷ",
      "lemma": "ὁ",
      "strongs": "G35880",
      "morph": "Gr,EA,,,,DMS,"
    },
    {
      "word": "Ἀληθινῷ",
      "lemma": "ἀληθινός",
      "strongs": "G02280",
      "morph": "Gr,NS,,,,DMS,"
    },
    {
      "word": "ἐν",
      "lemma": "ἐν",
      "strongs": "G17220",
      "morph": "Gr,P,,,,,D,,,"
    },
    {
      "word": "τῷ",
      "lemma": "ὁ",
      "strongs": "G35880",
      "morph": "Gr,EA,,,,DMS,"
    },
    {
      "word": "Υἱῷ",
      "lemma": "υἱός",
      "strongs": "G52070",
      "morph": "Gr,N,,,,,DMS,"
    },
    {
      "word": "αὐτοῦ",
      "lemma": "αὐτός",
      "strongs": "G08460",
      "morph": "Gr,RP,,,3GMS,"
    },
    {
      "word": "Ἰησοῦ",
      "lemma": "Ἰησοῦς",
      "strongs": "G24240",
      "morph": "Gr,N,,,,,DMS,"
    },
    {
      "word": "Χριστῷ",
      "lemma": "χριστός",
      "strongs": "G55470",
      "morph": "Gr,N,,,,,DMS,"
    },
    {
      "word": "οὗτός",
      "lemma": "οὗτος",
      "strongs": "G37780",
      "morph": "Gr,RD,,,,NMS,"
    },
    {
      "word": "ἐστιν",
      "lemma": "εἰμί",
      "strongs": "G15100",
      "morph": "Gr,V,IPA3,,S,"
    },
    {
      "word": "ὁ",
      "lemma": "ὁ",
      "strongs": "G35880",
      "morph": "Gr,EA,,,,NMS,"
    },
    {
      "word": "ἀληθινὸς",
      "lemma": "ἀληθινός",
      "strongs": "G02280",
      "morph": "Gr,AA,,,,NMS,"
    },
    {
      "word": "Θεὸς",
      "lemma": "θεός",
      "strongs": "G23160",
      "morph": "Gr,N,,,,,NMS,"
    },
    {
      "word": "καὶ",
      "lemma": "καί",
      "strongs": "G25320",
      "morph": "Gr,CC,,,,,,,,"
    },
    {
      "word": "ζωὴ",
      "lemma": "ζωή",
      "strongs": "G22220",
      "morph": "Gr,N,,,,,NFS,"
    },
    {
      "word": "αἰώνιος",
      "lemma": "αἰώνιος",
      "strongs": "G01660",
      "morph": "Gr,AA,,,,NFS,"
    }
  ],
  "21": [
    {
      "word": "τεκνία",
      "lemma": "τεκνίον",
      "strongs": "G50400",
      "morph": "Gr,N,,,,,VNPD"
    },
    {
      "word": "φυλάξατε",
      "lemma": "φυλάσσω",
      "strongs": "G54420",
      "morph": "Gr,V,MAA2,,P,"
    },
    {
      "word": "ἑαυτὰ",
      "lemma": "ἑαυτοῦ",
      "strongs": "G14380",
      "morph": "Gr,RE,,,2ANP,"
    },
    {
      "word": "ἀπὸ",
      "lemma": "ἀπό",
      "strongs": "G05750",
      "morph": "Gr,P,,,,,G,,,"
    },
    {
      "word": "τῶν",
      "lemma": "ὁ",
      "strongs": "G35880",
      "morph": "Gr,EA,,,,GNP,"
    },
    {
      "word": "εἰδώλων",
      "lemma": "εἴδωλον",
      "strongs": "G14970",
      "morph": "Gr,N,,,,,GNP,"
    }
  ]
}